parsnip/__init__.py
parsnip/_errors.py
parsnip/conftest.py
parsnip/parsnip.py
parsnip/patterns.py
parsnip_cif-0.4.1.dist-info/licenses/LICENSE
parsnip_cif-0.4.1.dist-info/METADATA
parsnip_cif-0.4.1.dist-info/WHEEL
parsnip_cif-0.4.1.dist-info/top_level.txt
parsnip_cif-0.4.1.dist-info/RECORD
