Metadata-Version: 2.4
Name: parsnip-cif
Version: 0.4.1
Summary: Minimal library for parsing CIF & mmCIF files in Python.
Author-email: Jen Bradley <jenbrad@umich.edu>
Project-URL: Source, https://github.com/glotzerlab/parsnip
Project-URL: Issues, https://github.com/glotzerlab/parsnip/issues
Keywords: Development Status :: 4 - Beta,License :: OSI Approved :: BSD License,Programming Language :: Python :: 3.7,Programming Language :: Python :: 3.8,Programming Language :: Python :: 3.9,Programming Language :: Python :: 3.10,Programming Language :: Python :: 3.11,Programming Language :: Python :: 3.12,Topic :: Scientific/Engineering :: Physics,Topic :: Scientific/Engineering :: Chemistry
Requires-Python: >=3.9
License-File: LICENSE
Requires-Dist: numpy>=1.19
Requires-Dist: more-itertools
Provides-Extra: tests
Requires-Dist: ase; extra == "tests"
Requires-Dist: gemmi; extra == "tests"
Requires-Dist: pycifrw!=5.0.0; extra == "tests"
Requires-Dist: pytest; extra == "tests"
Requires-Dist: pytest-doctestplus; extra == "tests"
Requires-Dist: pytest-xdist; extra == "tests"
Requires-Dist: setuptools; extra == "tests"
Requires-Dist: sympy; extra == "tests"
Requires-Dist: wheel; extra == "tests"
Provides-Extra: doc
Requires-Dist: autodocsumm; extra == "doc"
Requires-Dist: furo; extra == "doc"
Requires-Dist: numpy>=1.26.4; extra == "doc"
Requires-Dist: sphinx>=7.3.7; extra == "doc"
Requires-Dist: sphinx-copybutton; extra == "doc"
Requires-Dist: sphinx-notfound-page; extra == "doc"
Requires-Dist: pytest-doctestplus; extra == "doc"
Provides-Extra: sympy
Requires-Dist: sympy; extra == "sympy"
Dynamic: license-file
